
{
  "placeholderAudio": [
    {
      "id": "space-ambient",
      "description": "A low, deep, and continuous ambient hum of deep space.",
      "audioUrl": "https://kenney.nl/assets/digital-audio/space-ambient.mp3"
    },
    {
      "id": "scan-effect",
      "description": "A short, futuristic scanning sound effect.",
      "audioUrl": "https://kenney.nl/assets/digital-audio/sci-fi-bleep.mp3"
    },
    {
      "id": "proximity-hum",
      "description": "A low-frequency hum that can be used to indicate proximity to a large object.",
      "audioUrl": "https://kenney.nl/assets/digital-audio/engine-hum.mp3"
    },
    {
      "id": "ui-click",
      "description": "A simple, clean click sound for UI interactions.",
      "audioUrl": "https://kenney.nl/assets/ui-audio/click-3.mp3"
    },
    {
      "id": "ship-throttle",
      "description": "The continuous hum of a spaceship's engine throttling up or down.",
      "audioUrl": "https://kenney.nl/assets/digital-audio/engine-loop.mp3"
    }
  ]
}
